pamela.py
pamela-0.3.0.dist-info/DESCRIPTION.rst
pamela-0.3.0.dist-info/METADATA
pamela-0.3.0.dist-info/RECORD
pamela-0.3.0.dist-info/WHEEL
pamela-0.3.0.dist-info/metadata.json
pamela-0.3.0.dist-info/top_level.txt
