Metadata-Version: 1.1
Name: pamela
Version: 0.3.0
Summary: PAM interface using ctypes
Home-page: http://github.com/minrk/pamela
Author: Min RK
Author-email: benjaminrk@gmail.com
License: MIT
Keywords: pam,authentication
Platform: UNKNOWN
Classifier: Development Status :: 4 - Beta
Classifier: Intended Audience :: Developers
Classifier: License :: OSI Approved :: MIT License
Classifier: Operating System :: POSIX :: Linux
Classifier: Operating System :: MacOS :: MacOS X
Classifier: Programming Language :: Python
Classifier: Topic :: Software Development :: Libraries :: Python Modules
Classifier: Topic :: System :: Systems Administration :: Authentication/Directory
